pfapack-1.0.2.dist-info/METADATA
pfapack-1.0.2.dist-info/WHEEL
pfapack/libpfapack.dll
pfapack/libpfapack.dll.a
pfapack/libcpfapack.dll
pfapack/libcpfapack.dll.a
pfapack/__init__.py
pfapack/_version.py
pfapack/ctypes.py
pfapack/exceptions.py
pfapack/pfaffian.py
pfapack-1.0.2.dist-info/RECORD
