Metadata-Version: 2.1
Name: pfapack
Version: 1.0.2
Summary: Efficient numerical computation of the Pfaffian for dense and banded skew-symmetric matrices.
Author-Email: Bas Nijholt <bas@nijho.lt>, Michael Wimmer <m.t.wimmer@tudelft.nl>
License: MIT
Classifier: Intended Audience :: Science/Research
Classifier: Operating System :: OS Independent
Classifier: Programming Language :: Python
Classifier: Programming Language :: Python :: 3
Classifier: Programming Language :: Python :: 3.10
Classifier: Programming Language :: Python :: 3.11
Classifier: Programming Language :: Python :: 3.12
Classifier: Programming Language :: Python :: 3.13
Classifier: Topic :: Scientific/Engineering
Classifier: Topic :: Utilities
Classifier: License :: OSI Approved :: MIT License
Project-URL: homepage, https://github.com/basnijholt/pfapack
Project-URL: repository, https://github.com/basnijholt/pfapack
Project-URL: documentation, https://pfapack.readthedocs.io
Requires-Python: >=3.10
Requires-Dist: scipy
Requires-Dist: numpy
Provides-Extra: docs
Requires-Dist: sphinx; extra == "docs"
Requires-Dist: sphinx-rtd-theme; extra == "docs"
Requires-Dist: myst-parser; extra == "docs"
Requires-Dist: sphinxcontrib.apidoc; extra == "docs"
Provides-Extra: dev
Requires-Dist: pre-commit; extra == "dev"
Provides-Extra: test
Requires-Dist: pytest; extra == "test"
Requires-Dist: pytest-cov; extra == "test"
Requires-Dist: pytest-mypy; extra == "test"
Requires-Dist: tox; extra == "test"
